{
  "version": "0.1.0",
  "repo_url": "https://github.com/spipu/html2pdf",
  "commit": "119d660876546c6b496f8aa6490f1ab8111350f9",
  "length": 6518,
  "fraction_included": 1.0,
  "filenames": [
    "src/locale/ca.csv",
    "src/locale/cn.csv",
    "src/locale/cs.csv",
    "src/locale/da.csv",
    "src/locale/de.csv",
    "src/locale/en.csv",
    "src/locale/es.csv",
    "src/locale/fi.csv",
    "src/locale/fr.csv",
    "src/locale/it.csv",
    "src/locale/ja.csv",
    "src/locale/lt.csv",
    "src/locale/nl.csv",
    "src/locale/no.csv",
    "src/locale/pl.csv",
    "src/locale/pt.csv",
    "src/locale/ru.csv",
    "src/locale/tr.csv",
    "test/generate.sh"
  ]
}
