{
  "version": "0.1.0",
  "repo_url": "https://github.com/lota/phamm",
  "commit": "42e2a59b208e6c6660d81de0c70103403249bb55",
  "length": 121276,
  "fraction_included": 1.0,
  "filenames": [
    "examples/conf/postfix/fork.pl",
    "po/phamm.pot",
    "public/functions.js",
    "public/js/bootstrap.js",
    "tools/backup-basedn.sh",
    "tools/check_expiration.pl",
    "tools/cleaner.sh",
    "tools/greylist_recipients_whitelists_ldap.pl",
    "tools/handle_vacation.sh",
    "tools/insert-ldap.sh",
    "tools/lib_functions.sh",
    "tools/make-mail.sh",
    "tools/mod-ldap.sh",
    "tools/phamm-useradd.pl",
    "tools/vacation.py"
  ]
}
